jumpstarter_driver_energenie/__init__.py
jumpstarter_driver_energenie/driver.py
jumpstarter_driver_energenie/driver_test.py
jumpstarter_driver_energenie-0.7.4.dist-info/METADATA
jumpstarter_driver_energenie-0.7.4.dist-info/WHEEL
jumpstarter_driver_energenie-0.7.4.dist-info/entry_points.txt
jumpstarter_driver_energenie-0.7.4.dist-info/RECORD
