Metadata-Version: 2.4
Name: jumpstarter-driver-energenie
Version: 0.7.4
Summary: Energenie is an advanced surge protector with power management features
Project-URL: Homepage, https://jumpstarter.dev
Project-URL: source_archive, https://github.com/jumpstarter-dev/repo/archive/c5d38de69eadbb8eb0388bcfe3430a679fff0059.zip
Author-email: Enric Balletbo i Serra <eballetbo@redhat.com>
License: Apache-2.0
Requires-Python: >=3.11
Requires-Dist: anyio>=4.10.0
Requires-Dist: jumpstarter
Requires-Dist: jumpstarter-driver-power
